mc_players/__init__.py
mc_players/playerlist.py
mc_players-2.1.1.dist-info/entry_points.txt
mc_players-2.1.1.dist-info/LICENSE
mc_players-2.1.1.dist-info/METADATA
mc_players-2.1.1.dist-info/WHEEL
mc_players-2.1.1.dist-info/RECORD
