Metadata-Version: 2.1
Name: mc-players
Version: 2.1.1
Summary: List the player usernames that have signed to a Minecraft server lately
Home-page: https://github.com/jaydenmilne/minecraft-server-player-list
License: AGPL-3.0-or-later
Keywords: minecraft,paper,bukkit
Author: Jayden Milne
Author-email: jaydenmilne@users.noreply.github.com
Requires-Python: >=3.8,<4.0
Classifier: License :: OSI Approved :: GNU Affero General Public License v3
Classifier: License :: OSI Approved :: GNU Affero General Public License v3 or later (AGPLv3+)
Classifier: Operating System :: OS Independent
Classifier: Programming Language :: Python :: 3
Classifier: Programming Language :: Python :: 3.8
Classifier: Programming Language :: Python :: 3.9
Classifier: Programming Language :: Python :: 3.10
Classifier: Programming Language :: Python :: 3.11
Classifier: Programming Language :: Python :: 3
Classifier: Topic :: Games/Entertainment
Project-URL: Repository, https://github.com/jaydenmilne/minecraft-server-player-list
